pynasa/__init__.py
pynasa/cli/__init__.py
pynasa/cli/commands.py
pynasa/core/__init__.py
pynasa/core/api.py
pynasa/core/nasa.py
pynasa/tests/__init__.py
pynasa/tests/test_api.py
pynasa/tests/test_core.py
pynasa/tests/test_library.py
pynasa/utils/__init__.py
pynasa/utils/alerts.py
pynasa/utils/url.py
pynasa-1.0.2.dist-info/METADATA
pynasa-1.0.2.dist-info/WHEEL
pynasa-1.0.2.dist-info/entry_points.txt
pynasa-1.0.2.dist-info/top_level.txt
pynasa-1.0.2.dist-info/RECORD
